[
  {
    "href": "/notes/american-pride",
    "slug": "american-pride",
    "label": "American Pride",
    "description": "Why American pride is our greatest strength and greatest weakness.",
    "date": "2026-04-22"
  },
  {
    "href": "/notes/success-and-failures-of-federalism",
    "slug": "success-and-failures-of-federalism",
    "label": "Success and Failures of Federalism",
    "description": "Analyzing federalism's track record in American governance.",
    "date": "2026-04-23"
  },
  {
    "href": "/notes/the-absolute-rule-of-oligarchy",
    "slug": "the-absolute-rule-of-oligarchy",
    "label": "The Absolute Rule of Oligarchy",
    "description": "Exploring the tendency of power to concentrate in the hands of the few.",
    "date": "2026-04-23"
  },
  {
    "href": "/notes/the-role-of-decentralization-in-democracy",
    "slug": "the-role-of-decentralization-in-democracy",
    "label": "The Role of Decentralization in Democracy",
    "description": "Examining how decentralization enables democratic participation.",
    "date": "2026-04-23"
  },
  {
    "href": "/notes/economic-incentives-analysis",
    "slug": "economic-incentives-analysis",
    "label": "Economic Incentives Analysis",
    "description": "How economic incentives drive behavior in American politics.",
    "date": "2025-01-15"
  },
  {
    "href": "/notes/the-woes-of-interpositioning",
    "slug": "the-woes-of-interpositioning",
    "label": "The Woes of Interpositioning",
    "description": "Examining the doctrine of interposition and its problems.",
    "date": "2026-04-23"
  },
  {
    "href": "/notes/introduction-to-our-approach",
    "slug": "introduction-to-our-approach",
    "label": "Introduction to Our Approach",
    "description": "How incentive structures shape policy outcomes.",
    "date": "2025-01-01"
  },
  {
    "href": "/notes/healthcare-market-failures",
    "slug": "healthcare-market-failures",
    "label": "Healthcare Market Failures",
    "description": "The structural failures in American healthcare markets explained.",
    "date": "2025-02-01"
  }
]